multithreaded/__init__.py
multithreaded/multithreaded.py
multithreaded/communication/__init__.py
multithreaded/communication/module.py
multithreaded/synchronization/__init__.py
multithreaded/synchronization/module.py
multithreaded-0.0.6.dist-info/METADATA
multithreaded-0.0.6.dist-info/WHEEL
multithreaded-0.0.6.dist-info/top_level.txt
multithreaded-0.0.6.dist-info/RECORD
