Metadata-Version: 2.1
Name: multithreaded
Version: 0.0.6
Summary: advanced threading made beginner... threading library that expands upon stdlib "threading."
Home-page: https://github.com/Noah018dev/multithreaded
Author: Noah018
Author-email: noahc018@pm.me
License: This is free and unencumbered software released into the public domain.
Classifier: Programming Language :: Python :: 3
Requires-Dist: cloudpickle
Requires-Dist: logzero
Requires-Dist: stop-thread
